coauthors/__init__.py
coauthors/coauthors.py
coauthors-0.8.dist-info/METADATA
coauthors-0.8.dist-info/RECORD
coauthors-0.8.dist-info/WHEEL
coauthors-0.8.dist-info/entry_points.txt
coauthors-0.8.dist-info/top_level.txt
