Metadata-Version: 2.1
Name: coauthors
Version: 0.8
Summary: Add coauthors to your last git commit message.
Home-page: https://github.com/quiqueporta/coauthors
Author: Quique Porta
Author-email: quiqueporta@gmail.com
License: GPLv3
Download-URL: https://github.com/quiqueporta/coauthors/releases
Platform: UNKNOWN
Classifier: Development Status :: 4 - Beta
Classifier: Environment :: Console
Classifier: Intended Audience :: Developers
Classifier: License :: OSI Approved :: MIT License
Classifier: Operating System :: OS Independent
Classifier: Programming Language :: Python
Classifier: Topic :: Utilities
Requires-Dist: gitpython
